equilibrator_cache/__init__.py
equilibrator_cache/api.py
equilibrator_cache/compatibility.py
equilibrator_cache/compound_cache.py
equilibrator_cache/exceptions.py
equilibrator_cache/reaction.py
equilibrator_cache/thermodynamic_constants.py
equilibrator_cache/zenodo.py
equilibrator_cache/models/__init__.py
equilibrator_cache/models/compound.py
equilibrator_cache/models/compound_identifier.py
equilibrator_cache/models/compound_microspecies.py
equilibrator_cache/models/magnesium_dissociation_constant.py
equilibrator_cache/models/mixins.py
equilibrator_cache/models/registry.py
equilibrator_cache-0.6.2.dist-info/licenses/LICENSE
equilibrator_cache-0.6.2.dist-info/METADATA
equilibrator_cache-0.6.2.dist-info/WHEEL
equilibrator_cache-0.6.2.dist-info/top_level.txt
equilibrator_cache-0.6.2.dist-info/RECORD
