Metadata-Version: 2.4
Name: equilibrator-cache
Version: 0.6.2
Summary: Cache application for compounds, reactions, and enzymes
Author: Elad Noor, Moritz E. Beber
License: MIT License
Project-URL: repository, https://gitlab.com/equilibrator/equilibrator-cache/
Project-URL: documentation, https://equilibrator.readthedocs.io/en/latest/
Keywords: component contribution,Gibbs energy,biochemical reaction,eQuilibrator,cache
Classifier: Development Status :: 4 - Beta
Classifier: Intended Audience :: Science/Research
Classifier: Topic :: Scientific/Engineering :: Bio-Informatics
Classifier: Topic :: Scientific/Engineering :: Chemistry
Classifier: License :: OSI Approved :: MIT License
Classifier: Natural Language :: English
Classifier: Operating System :: OS Independent
Classifier: Programming Language :: Python :: 3 :: Only
Classifier: Programming Language :: Python :: 3.9
Classifier: Programming Language :: Python :: 3.10
Classifier: Programming Language :: Python :: 3.11
Classifier: Programming Language :: Python :: 3.12
Classifier: Programming Language :: Python :: 3.13
Requires-Python: >=3.9
License-File: LICENSE
Requires-Dist: sqlalchemy~=2.0
Requires-Dist: numpy>=2.0
Requires-Dist: scipy>=1.12
Requires-Dist: pandas>=2.0
Requires-Dist: pyarrow>=21.0
Requires-Dist: Levenshtein~=0.27
Requires-Dist: pint~=0.24
Requires-Dist: tqdm~=4.0
Requires-Dist: appdirs~=1.4
Requires-Dist: pooch~=1.8
Provides-Extra: test
Requires-Dist: pytest; extra == "test"
Requires-Dist: pytest-cov; extra == "test"
Requires-Dist: pytest-raises; extra == "test"
Requires-Dist: pytest-mock; extra == "test"
Requires-Dist: hypothesis; extra == "test"
Provides-Extra: development
Requires-Dist: black; extra == "development"
Requires-Dist: isort; extra == "development"
Requires-Dist: flake8; extra == "development"
Requires-Dist: safety; extra == "development"
Requires-Dist: tox; extra == "development"
Requires-Dist: twine; extra == "development"
Provides-Extra: deployment
Requires-Dist: click; extra == "deployment"
Requires-Dist: click-log; extra == "deployment"
Requires-Dist: openbabel; extra == "deployment"
Requires-Dist: python-dateutil; extra == "deployment"
Dynamic: license-file
